README
setup.py
django_ms_utils.egg-info/PKG-INFO
django_ms_utils.egg-info/SOURCES.txt
django_ms_utils.egg-info/dependency_links.txt
django_ms_utils.egg-info/requires.txt
django_ms_utils.egg-info/top_level.txt
ms_utils/__init__.py
ms_utils/apps.py
ms_utils/columns.py
ms_utils/fields.py
ms_utils/filters.py
ms_utils/menu.py
ms_utils/tables.py
ms_utils/urls.py
ms_utils/widgets.py
ms_utils/static/ms_utils/css/AdminLTE.min.css
ms_utils/static/ms_utils/css/animate.css
ms_utils/static/ms_utils/css/bootstrap-datepicker3.min.css
ms_utils/static/ms_utils/css/bootstrap.min.css
ms_utils/static/ms_utils/css/daterangepicker.css
ms_utils/static/ms_utils/css/font-awesome.min.css
ms_utils/static/ms_utils/css/jquery.timepicker.css
ms_utils/static/ms_utils/css/login.css
ms_utils/static/ms_utils/css/ms_utils.css
ms_utils/static/ms_utils/css/multi-select.css
ms_utils/static/ms_utils/css/select2.min.css
ms_utils/static/ms_utils/css/skins/skin-all.min.css
ms_utils/static/ms_utils/fonts/FontAwesome.otf
ms_utils/static/ms_utils/fonts/fontawesome-webfont.eot
ms_utils/static/ms_utils/fonts/fontawesome-webfont.svg
ms_utils/static/ms_utils/fonts/fontawesome-webfont.ttf
ms_utils/static/ms_utils/fonts/fontawesome-webfont.woff
ms_utils/static/ms_utils/fonts/fontawesome-webfont.woff2
ms_utils/static/ms_utils/fonts/glyphicons-halflings-regular.eot
ms_utils/static/ms_utils/fonts/glyphicons-halflings-regular.svg
ms_utils/static/ms_utils/fonts/glyphicons-halflings-regular.ttf
ms_utils/static/ms_utils/fonts/glyphicons-halflings-regular.woff
ms_utils/static/ms_utils/fonts/glyphicons-halflings-regular.woff2
ms_utils/static/ms_utils/images/logo_default.png
ms_utils/static/ms_utils/images/logo_icon_default.png
ms_utils/static/ms_utils/images/profile_default.jpg
ms_utils/static/ms_utils/js/app.min.js
ms_utils/static/ms_utils/js/bootstrap-datepicker.min.js
ms_utils/static/ms_utils/js/bootstrap-notify.min.js
ms_utils/static/ms_utils/js/bootstrap.min.js
ms_utils/static/ms_utils/js/daterangepicker.js
ms_utils/static/ms_utils/js/jquery.min.js
ms_utils/static/ms_utils/js/jquery.multi-select.js
ms_utils/static/ms_utils/js/jquery.timepicker.js
ms_utils/static/ms_utils/js/moment.js
